{
  "success": true,
  "data": [
    {
      "id": "rss_0",
      "title": "中職》樂天兩位新洋砲皆來台比賽過 道威聖還曾對兄弟開轟",
      "description": "樂天桃猿今天正式宣布洋砲加盟，除了日前提前被揭露、已來台報到的Ronnie Dawson，還另找來曾效力美國獨立聯盟和日職讀賣巨人的Adam Walker，分別譯名為「道威聖」與「威克」。道威聖曾效力韓職培證英雄兩季，威克則是效力過日職巨人、軟銀，今年加盟日職二軍聯盟的隊伍Oisix新潟天鵝之皇隊。",
      "link": "https://tw.sports.yahoo.com/news/%E4%B8%AD%E8%81%B7-%E6%A8%82%E5%A4%A9%E5%85%A9%E4%BD%8D%E6%96%B0%E6%B4%8B%E7%A0%B2%E7%9A%86%E4%BE%86%E5%8F%B0%E6%AF%94%E8%B3%BD%E9%81%8E-%E9%81%93%E5%A8%81%E8%81%96%E9%82%84%E6%9B%BE%E5%B0%8D%E5%85%84%E5%BC%9F%E9%96%8B%E8%BD%9F-142634470.html",
      "pubDate": "7/6 6:26",
      "rawImg": "",
      "fallbackImg": "https://images.unsplash.com/photo-1544620347-c4fd4a3d5957?auto=format&fit=crop&w=1200&q=80"
    },
    {
      "id": "rss_1",
      "title": "MLB／大谷明星賽球員票不敵史瓦伯 費城球迷得意：懂棒球的人都知道",
      "description": "今年大聯盟明星賽指定打擊部門的球員間投票結果出爐，洛杉磯道奇球星大谷翔平雖然在球迷票選中拿下兩聯盟最高票，早早確定以先發身分出賽，但在球員間投票中，他以些微差距不敵費城人強打史瓦伯（Kyle S...",
      "link": "https://tw.sports.yahoo.com/news/mlb%EF%BC%8F%E5%A4%A7%E8%B0%B7%E6%98%8E%E6%98%9F%E8%B3%BD%E7%90%83%E5%93%A1%E7%A5%A8%E4%B8%8D%E6%95%B5%E5%8F%B2%E7%93%A6%E4%BC%AF-%E8%B2%BB%E5%9F%8E%E7%90%83%E8%BF%B7%E5%BE%97%E6%84%8F%EF%BC%9A%E6%87%82%E6%A3%92%E7%90%83%E7%9A%84%E4%BA%BA%E9%83%BD%E7%9F%A5%E9%81%93-111417636.html",
      "pubDate": "7/6 3:14",
      "rawImg": "https://s.yimg.com/os/creatr-uploaded-images/2026-07/81cfd090-7954-11f1-b6cf-a233bbbf0442",
      "fallbackImg": "https://images.unsplash.com/photo-1558000143-a6217b1b3699?auto=format&fit=crop&w=1200&q=80"
    },
    {
      "id": "rss_2",
      "title": "NBA》灰熊3年9.6億約搶波斯特 勇士若跟進恐無法簽詹皇",
      "description": "根據《ESPN》記者查拉尼亞（Shams Charania）報導指出，勇士受限自由球員波斯特（Quinten Post）已經獲得灰熊隊3年3000萬美元（約新台幣9.6億元...…",
      "link": "https://sports.ltn.com.tw/news/breakingnews/5496096",
      "pubDate": "7/6 15:11",
      "rawImg": "",
      "fallbackImg": "https://images.unsplash.com/photo-1544620347-c4fd4a3d5957?auto=format&fit=crop&w=1200&q=80"
    },
    {
      "id": "rss_3",
      "title": "日職》徐若熙腰部恐動刀？ 軟銀投教：投不了球是事實",
      "description": "效力軟銀鷹的25歲台灣強投徐若熙，日前因腰部不適延後先發登板，更傳出他月中將動刀治療。對此，軟銀投手首席教練倉野信次受訪坦言，接下來才會收到相關報告。\n\n\n徐若熙今年以3年...…",
      "link": "https://sports.ltn.com.tw/news/breakingnews/5495840",
      "pubDate": "7/6 10:14",
      "rawImg": "",
      "fallbackImg": "https://images.unsplash.com/photo-1494522855154-9297ac14b55f?auto=format&fit=crop&w=1200&q=80"
    },
    {
      "id": "rss_4",
      "title": "MLB》盛讚二刀流大谷是終極獨角獸 A-Rod：史上最強版本",
      "description": "道奇日本二刀流巨星大谷翔平在今年高票當選明星賽人氣王，將擔任國聯指定打擊，雖然無緣入選先發投手。但傳奇名將「A-Rod」羅德里奎茲（Alex Rodriguez）仍盛讚：「...…",
      "link": "https://sports.ltn.com.tw/news/breakingnews/5495663",
      "pubDate": "7/6 9:43",
      "rawImg": "",
      "fallbackImg": "https://images.unsplash.com/photo-1579952363873-27f3bade9f55?auto=format&fit=crop&w=1200&q=80"
    },
    {
      "id": "rss_5",
      "title": "中職》兄弟本土王牌鄭浩均歸隊！明天先發出戰統一獅",
      "description": "中職今天休兵、明天進行2場比賽，中信兄弟預計客場出戰統一獅，日前因傷下二軍大約1個月的鄭浩均，明天將歸隊並先發出戰獅隊。\n\n\n鄭浩均本季出賽10場，戰績3勝3敗、防禦率5...…",
      "link": "https://sports.ltn.com.tw/news/breakingnews/5495770",
      "pubDate": "7/6 9:23",
      "rawImg": "",
      "fallbackImg": "https://images.unsplash.com/photo-1508344928928-7137b29de216?auto=format&fit=crop&w=1200&q=80"
    },
    {
      "id": "rss_6",
      "title": "中職》「在台灣繼續為你們加油！」 樂天新洋砲威克對前東家新潟充滿感謝",
      "description": "樂天桃猿今天一次官宣道威聖、威克兩位新洋砲。其中，曾效力日職讀賣巨人的威克，今年效力日職二軍聯盟的隊伍Oisix新潟天鵝之皇隊。稍早在該隊官網，威克透過球團，表達對球隊和...…",
      "link": "https://sports.ltn.com.tw/news/breakingnews/5495563",
      "pubDate": "7/6 7:17",
      "rawImg": "",
      "fallbackImg": "https://images.unsplash.com/photo-1544620347-c4fd4a3d5957?auto=format&fit=crop&w=1200&q=80"
    },
    {
      "id": "rss_7",
      "title": "中職》主力陳晨威將打亞運 樂天備雙洋砲有理由",
      "description": "樂天桃猿今日正式宣布，與外籍野手Ronnie Dawson及Adam Walker達成加盟共識，中文譯名分別暫定為「道威聖」與「威克」。罕見一次補強兩位外籍野手，為加強上...…",
      "link": "https://sports.ltn.com.tw/news/breakingnews/5495488",
      "pubDate": "7/6 6:29",
      "rawImg": "",
      "fallbackImg": "https://images.unsplash.com/photo-1558000143-a6217b1b3699?auto=format&fit=crop&w=1200&q=80"
    },
    {
      "id": "rss_8",
      "title": "中職》洲際球場成潮流城市 潮牌AAPE×中信兄弟《TAICHUNG BROS CITY》限時開城！",
      "description": "Street Vibes on Field!在棒球場展現你的街頭潮流態度！中信兄弟將於7月25日至7月26日在臺中洲際棒球場攜手國際潮流品牌 AAPE BY *A BATHIN...…",
      "link": "https://sports.ltn.com.tw/news/breakingnews/5495457",
      "pubDate": "7/6 6:08",
      "rawImg": "",
      "fallbackImg": "https://images.unsplash.com/photo-1494522855154-9297ac14b55f?auto=format&fit=crop&w=1200&q=80"
    }
  ]
}