{
  "success": true,
  "data": [
    {
      "id": "rss_0",
      "title": "中職／日職明星賽票選偏戰績看成績 中職卻無視這兩項",
      "description": "日職明星賽的球迷票選將於28日截止，最新的中間票選情形在12日公布，兩聯盟呈現不太相同的狀態。 央聯的中間發表名單上出現了不少新面孔，先發投手的第一名是養樂多的山野太一，山野是20年的第二指名，...",
      "link": "https://tw.sports.yahoo.com/news/%E4%B8%AD%E8%81%B7-%E6%97%A5%E8%81%B7%E6%98%8E%E6%98%9F%E8%B3%BD%E7%A5%A8%E9%81%B8%E5%81%8F%E6%88%B0%E7%B8%BE%E7%9C%8B%E6%88%90%E7%B8%BE-%E4%B8%AD%E8%81%B7%E5%8D%BB%E7%84%A1%E8%A6%96%E9%80%99%E5%85%A9%E9%A0%85-230000859.html",
      "pubDate": "6/15 15:00",
      "rawImg": "",
      "fallbackImg": "https://images.unsplash.com/photo-1544620347-c4fd4a3d5957?auto=format&fit=crop&w=1200&q=80"
    }
  ]
}