{
  "success": true,
  "data": [
    {
      "id": "rss_0",
      "title": "中職》陳昱勛傳出不參加選秀要旅外 葉君璋：總比選進來了才出去要好",
      "description": "2026年中華職棒季中選秀會將於明天（29日）舉行，今天傳出高苑工商投手陳昱勛收到美聯球隊報價預計退出選秀，聯盟對此回覆，尚未接獲選手或經紀公司的相關訊息，味全龍總教練葉君璋表示，如果在選秀前決定退出，總比選進來才出去要好。葉君璋指出，味全球團已經開過會幾次會議，雖然第1輪有好幾個人選，但是尚未正式",
      "link": "https://tw.sports.yahoo.com/news/%E4%B8%AD%E8%81%B7-%E9%99%B3%E6%98%B1%E5%8B%9B%E5%82%B3%E5%87%BA%E4%B8%8D%E5%8F%83%E5%8A%A0%E9%81%B8%E7%A7%80%E8%A6%81%E6%97%85%E5%A4%96-%E8%91%89%E5%90%9B%E7%92%8B-%E7%B8%BD%E6%AF%94%E9%81%B8%E9%80%B2%E4%BE%86%E4%BA%86%E6%89%8D%E5%87%BA%E5%8E%BB%E8%A6%81%E5%A5%BD-093728532.html",
      "pubDate": "6/28 1:37",
      "rawImg": "https://media.zenfs.com/ko/libertytimes_786/f352923f643c9ef4b0ef388c58cdb71f",
      "fallbackImg": "https://images.unsplash.com/photo-1544620347-c4fd4a3d5957?auto=format&fit=crop&w=1200&q=80"
    },
    {
      "id": "rss_1",
      "title": "中職》新莊下起暴雨 富邦悍將對味全龍保留比賽開賽時間未定",
      "description": "富邦悍將表定今天下午17:05與味全龍進行保留比賽，受到新莊地區在開賽前半小時突然下起暴雨的影響，實際開打時間要視雨勢何時停止而定。這場比賽原本在6月9日進行，因雨延到6月25日補賽，打到5局上1出局，因為雷雨交加裁定保留，雙方比數仍是0：0，今天若能恢復比賽，將從味全第9棒曾聖安1好1壞繼續進行。",
      "link": "https://tw.sports.yahoo.com/news/%E4%B8%AD%E8%81%B7-%E6%96%B0%E8%8E%8A%E4%B8%8B%E8%B5%B7%E6%9A%B4%E9%9B%A8-%E5%AF%8C%E9%82%A6%E6%82%8D%E5%B0%87%E5%B0%8D%E5%91%B3%E5%85%A8%E9%BE%8D%E4%BF%9D%E7%95%99%E6%AF%94%E8%B3%BD%E9%96%8B%E8%B3%BD%E6%99%82%E9%96%93%E6%9C%AA%E5%AE%9A-085351488.html",
      "pubDate": "6/28 0:53",
      "rawImg": "https://media.zenfs.com/ko/libertytimes_786/3c4c934afae611acb76660ed6269e8c3",
      "fallbackImg": "https://images.unsplash.com/photo-1558000143-a6217b1b3699?auto=format&fit=crop&w=1200&q=80"
    },
    {
      "id": "rss_2",
      "title": "悍將林澤彬巧打　得點圈掌握高 (圖)",
      "description": "中華職棒富邦悍將隊野手林澤彬（圖）今年得點圈打擊表現優異，打擊教練高國輝也感到意外，直言喜歡這樣類型的選手。",
      "link": "https://tw.sports.yahoo.com/news/%E6%82%8D%E5%B0%87%E6%9E%97%E6%BE%A4%E5%BD%AC%E5%B7%A7%E6%89%93-%E5%BE%97%E9%BB%9E%E5%9C%88%E6%8E%8C%E6%8F%A1%E9%AB%98-%E5%9C%96-080408928.html",
      "pubDate": "6/28 0:04",
      "rawImg": "https://media.zenfs.com/zh-tw/cna.com.tw/064c364ecce98ac382cd4539bcda09d8",
      "fallbackImg": "https://images.unsplash.com/photo-1494522855154-9297ac14b55f?auto=format&fit=crop&w=1200&q=80"
    },
    {
      "id": "rss_3",
      "title": "中職》明天以「家長」身分出席選秀 陳品宏：弟弟沒被富邦選到，帶去的帽子就收起來",
      "description": "富邦悍將投手陳品宏明天將以「家長」的身分，陪同父母親前往選秀會場，見證弟弟陳柏凱獲得職棒球隊指名，他表示，會把自己選秀那頂帽子帶去，如果弟弟沒被富邦選到，就把帽子收起來。陳品宏於2024年季中選秀會第4輪被富邦指名，當時他隨U23世界盃培訓隊前往美國參加NCAA移地訓練賽沒法到場，由於弟弟陳柏凱參加",
      "link": "https://tw.sports.yahoo.com/news/%E4%B8%AD%E8%81%B7-%E6%98%8E%E5%A4%A9%E4%BB%A5-%E5%AE%B6%E9%95%B7-%E8%BA%AB%E5%88%86%E5%87%BA%E5%B8%AD%E9%81%B8%E7%A7%80-%E9%99%B3%E5%93%81%E5%AE%8F-075345686.html",
      "pubDate": "6/27 23:53",
      "rawImg": "https://media.zenfs.com/ko/libertytimes_786/29c61e1ea33984a6448a3d07dffdd801",
      "fallbackImg": "https://images.unsplash.com/photo-1579952363873-27f3bade9f55?auto=format&fit=crop&w=1200&q=80"
    },
    {
      "id": "rss_4",
      "title": "中職》兄弟下放第1指名大物！ 拉上二軍雙冠王曾頌恩",
      "description": "中職官網顯示，中信兄弟今天做出球員異動，下放第一指名大物許庭綸，拉上曾頌恩。\n\n\n曾頌恩在5月8日被下放後，這段時間在二軍有不錯的打擊表現，目前累積6轟、22分打點暫居雙冠...…",
      "link": "https://sports.ltn.com.tw/news/breakingnews/5486954",
      "pubDate": "6/28 9:18",
      "rawImg": "",
      "fallbackImg": "https://images.unsplash.com/photo-1558000143-a6217b1b3699?auto=format&fit=crop&w=1200&q=80"
    },
    {
      "id": "rss_5",
      "title": "MLB》大谷翔平連3戰敲安、山本由伸6局好投！道奇單局9分海扁教士",
      "description": "道奇日本王牌山本由伸今天對教士繳出6局優質先發，加上打線力挺，在6局上單局3轟一口氣灌進9分，最終衛冕軍以本季新高的15：3痛扁對手，山本進帳本季第8勝。\n\n\n道奇2局上靠...…",
      "link": "https://sports.ltn.com.tw/news/breakingnews/5486599",
      "pubDate": "6/28 3:49",
      "rawImg": "",
      "fallbackImg": "https://images.unsplash.com/photo-1508344928928-7137b29de216?auto=format&fit=crop&w=1200&q=80"
    },
    {
      "id": "rss_6",
      "title": "MLB》本季打擊率不到1成慘遭釋出！40歲335轟明星重砲找到新東家",
      "description": "根據《ESPN》知名記者帕桑（Carlos Santana）報導，日前遭響尾蛇釋出的40歲的明星重砲桑塔納（Carlos Santana），將與勇士簽下小聯盟合約，延續生涯...…",
      "link": "https://sports.ltn.com.tw/news/breakingnews/5486612",
      "pubDate": "6/28 2:54",
      "rawImg": "",
      "fallbackImg": "https://images.unsplash.com/photo-1544620347-c4fd4a3d5957?auto=format&fit=crop&w=1200&q=80"
    }
  ]
}