{
  "success": true,
  "data": [
    {
      "id": "rss_0",
      "title": "中職》把握獅隊兩次守備瑕疵 兄弟週末兩戰皆捷！",
      "description": "中信兄弟今和統一獅交手，雙方一度鏖戰到4:4平手，獅隊8局上內野守備大亂，兩度出現原本能抓下跑者的守備瑕疵，兄弟靠著宋晟睿高飛犧牲打和張仁瑋安打，終場兄弟6:4贏球，週末兩場都拿下。銳力獅首局連拿兩出局，卻被許基宏擊出二壘打，詹子賢擊出飛球出局，讓銳力獅度過得點圈有人失分危機。",
      "link": "https://tw.sports.yahoo.com/news/%E4%B8%AD%E8%81%B7-%E6%8A%8A%E6%8F%A1%E7%8D%85%E9%9A%8A%E5%85%A9%E6%AC%A1%E5%AE%88%E5%82%99%E7%91%95%E7%96%B5-%E5%85%84%E5%BC%9F%E9%80%B1%E6%9C%AB%E5%85%A9%E6%88%B0%E7%9A%86%E6%8D%B7-112133816.html",
      "pubDate": "6/21 3:21",
      "rawImg": "",
      "fallbackImg": "https://images.unsplash.com/photo-1544620347-c4fd4a3d5957?auto=format&fit=crop&w=1200&q=80"
    },
    {
      "id": "rss_1",
      "title": "林安可日職二軍敲第5轟　林家正演出單場雙安",
      "description": "（中央社記者蘇志畬台北21日電）日本職棒埼玉西武獅隊台灣野手林安可今天開轟，在二軍已累積5轟；而北海道火腿鬥士隊的林家正，也在二軍有單場雙安演出。",
      "link": "https://tw.sports.yahoo.com/news/%E6%9E%97%E5%AE%89%E5%8F%AF%E6%97%A5%E8%81%B7%E4%BA%8C%E8%BB%8D%E6%95%B2%E7%AC%AC5%E8%BD%9F-%E6%9E%97%E5%AE%B6%E6%AD%A3%E6%BC%94%E5%87%BA%E5%96%AE%E5%A0%B4%E9%9B%99%E5%AE%89-110636392.html",
      "pubDate": "6/21 3:06",
      "rawImg": "",
      "fallbackImg": "https://images.unsplash.com/photo-1558000143-a6217b1b3699?auto=format&fit=crop&w=1200&q=80"
    },
    {
      "id": "rss_2",
      "title": "中職》富邦悍將上半季最大驚奇 後藤光尊點名王苡丞",
      "description": "富邦悍將雖已無緣上半季冠軍，今年仍打出「不一樣」的戰績，今天若擊敗樂天桃猿將繼2022年下半季後，拿到最近6年第2次半季30勝，回顧上半季最大驚奇，總教練後藤光尊他毫不猶豫地說：「王苡丞！」後藤指出，原本只是希望王苡丞持續在二軍發揮長打實力，沒想到卻有辦法在一軍打出目前的成績，對球隊是相當正面的收穫",
      "link": "https://tw.sports.yahoo.com/news/%E4%B8%AD%E8%81%B7-%E5%AF%8C%E9%82%A6%E6%82%8D%E5%B0%87%E4%B8%8A%E5%8D%8A%E5%AD%A3%E6%9C%80%E5%A4%A7%E9%A9%9A%E5%A5%87-%E5%BE%8C%E8%97%A4%E5%85%89%E5%B0%8A%E9%BB%9E%E5%90%8D%E7%8E%8B%E8%8B%A1%E4%B8%9E-110425504.html",
      "pubDate": "6/21 3:04",
      "rawImg": "https://media.zenfs.com/ko/libertytimes_786/2cb54709be3257b675e16e598adfb294",
      "fallbackImg": "https://images.unsplash.com/photo-1494522855154-9297ac14b55f?auto=format&fit=crop&w=1200&q=80"
    },
    {
      "id": "rss_3",
      "title": "中職》台鋼砸6600萬值得！黃子鵬鎖龍飆神紀錄 近20年僅1人達陣",
      "description": "台鋼雄鷹季前砸5年6600萬元簽下的黃子鵬，今天對味全龍威風八面，先發6局無失分，連續22局無失分，寫下2023年江少慶以來，本土投手最長先發局數無失分紀錄。黃子鵬在13日完封富邦悍將，今天再封鎖甫封王的味全龍，前3局僅被敲1安。4局上被敲雙安，仍在一二壘有人連續抓下2出局，並在5至6局僅被擊出1支",
      "link": "https://tw.sports.yahoo.com/news/%E4%B8%AD%E8%81%B7-%E5%8F%B0%E9%8B%BC%E7%A0%B86600%E8%90%AC%E5%80%BC%E5%BE%97-%E9%BB%83%E5%AD%90%E9%B5%AC%E9%8E%96%E9%BE%8D%E9%A3%86%E7%A5%9E%E7%B4%80%E9%8C%84-%E8%BF%9120%E5%B9%B4%E5%83%851%E4%BA%BA%E9%81%94%E9%99%A3-104838745.html",
      "pubDate": "6/21 2:48",
      "rawImg": "",
      "fallbackImg": "https://images.unsplash.com/photo-1579952363873-27f3bade9f55?auto=format&fit=crop&w=1200&q=80"
    },
    {
      "id": "rss_4",
      "title": "中職／怎麼從短槍變大砲？　林智勝教學「練初速」！點最佳龍模範生是他",
      "description": "味全龍20日4：0完封台鋼雄鷹上半季冠軍終於到手，一軍助理打擊教練林智勝也親揭球隊本季全壘打數暴增的原因，他透露關鍵在增加擊球初速，更直呼隊上重砲劉基鴻是把這件事執行最淋漓盡致的球員。",
      "link": "https://tw.sports.yahoo.com/news/%E4%B8%AD%E8%81%B7%EF%BC%8F%E6%80%8E%E9%BA%BC%E5%BE%9E%E7%9F%AD%E6%A7%8D%E8%AE%8A%E5%A4%A7%E7%A0%B2%EF%BC%9F-%E6%9E%97%E6%99%BA%E5%8B%9D%E6%95%99%E5%AD%B8%E3%80%8C%E7%B7%B4%E5%88%9D%E9%80%9F%E3%80%8D%EF%BC%81%E9%BB%9E%E6%9C%80%E4%BD%B3%E9%BE%8D%E6%A8%A1%E7%AF%84%E7%94%9F%E6%98%AF%E4%BB%96-104000943.html",
      "pubDate": "6/21 2:40",
      "rawImg": "https://media.zenfs.com/zh-tw/setn.com.tw/b35e22d989030a8355714bb47d20b64a",
      "fallbackImg": "https://images.unsplash.com/photo-1508344928928-7137b29de216?auto=format&fit=crop&w=1200&q=80"
    },
    {
      "id": "rss_5",
      "title": "中職》王念好生涯首次守二壘 只剩中外野還沒守過",
      "description": "王念好於6月19日在洲際對中信兄弟8局下從三壘移防二壘，生涯在4個內野守備位置全部解鎖，他表示，總教練後藤光尊早就想讓他嘗試二壘，現在只剩下中外野還沒守過。王念好指出，2023年在秋訓自辦賽，曾被時任總教練陳金鋒安排替補守二壘，今年後藤接任總教練後，希望野手多嘗試不同守備位置，5月13日在洲際本季首",
      "link": "https://tw.sports.yahoo.com/news/%E4%B8%AD%E8%81%B7-%E7%8E%8B%E5%BF%B5%E5%A5%BD%E7%94%9F%E6%B6%AF%E9%A6%96%E6%AC%A1%E5%AE%88%E4%BA%8C%E5%A3%98-%E5%8F%AA%E5%89%A9%E4%B8%AD%E5%A4%96%E9%87%8E%E9%82%84%E6%B2%92%E5%AE%88%E9%81%8E-103503978.html",
      "pubDate": "6/21 2:35",
      "rawImg": "https://media.zenfs.com/zh-tw/libertytimes_786/39521344f2b48cfe8034cd70d6e6dae1",
      "fallbackImg": "https://images.unsplash.com/photo-1544620347-c4fd4a3d5957?auto=format&fit=crop&w=1200&q=80"
    },
    {
      "id": "rss_6",
      "title": "中職》郭泰源講中文讓「漫才少爺」嚇到！OB Talk show「笑」果十足",
      "description": "統一7-ELEVEN獅六月壓軸主題日「2026台日雙獅好友主題日」，與日職埼玉西武獅交流邁入第十一年，今年場內外活動升級，不僅邀請西武獅黃金世代OB渡邊久信、潮崎哲也、工藤公康來台和球迷分享對台灣的想法和印象，闖關活動和賽前表演也十分有看頭。",
      "link": "https://tw.sports.yahoo.com/news/%E4%B8%AD%E8%81%B7-%E9%83%AD%E6%B3%B0%E6%BA%90%E8%AC%9B%E4%B8%AD%E6%96%87%E8%AE%93-%E6%BC%AB%E6%89%8D%E5%B0%91%E7%88%BA-%E5%9A%87%E5%88%B0-ob-101433887.html",
      "pubDate": "6/21 2:14",
      "rawImg": "",
      "fallbackImg": "https://images.unsplash.com/photo-1558000143-a6217b1b3699?auto=format&fit=crop&w=1200&q=80"
    },
    {
      "id": "rss_7",
      "title": "中職》鈴木駿輔對前東家投出生涯初完封 陳晨威：以為是山本由伸",
      "description": "富邦悍將鈴木駿輔昨用101球獨撐9局，投出來台3年第1場完封勝，全場讓樂天桃猿打者上壘2次，若非陳晨威先敲安打再獲保送，有機會挑戰無安打比賽甚至是完全比賽，陳晨威不禁打趣說：「以為對到山本由伸。」陳晨威指出，鈴木與打者對決的心態很強，面對每位打者都全力投球，直球與指叉球在低角度進壘時，讓打者很難出棒",
      "link": "https://tw.sports.yahoo.com/news/%E4%B8%AD%E8%81%B7-%E9%88%B4%E6%9C%A8%E9%A7%BF%E8%BC%94%E5%B0%8D%E5%89%8D%E6%9D%B1%E5%AE%B6%E6%8A%95%E5%87%BA%E7%94%9F%E6%B6%AF%E5%88%9D%E5%AE%8C%E5%B0%81-%E9%99%B3%E6%99%A8%E5%A8%81-%E4%BB%A5%E7%82%BA%E6%98%AF%E5%B1%B1%E6%9C%AC%E7%94%B1%E4%BC%B8-100411813.html",
      "pubDate": "6/21 2:04",
      "rawImg": "https://media.zenfs.com/ko/libertytimes_786/10b2cbda1aac22a9649659714df852a5",
      "fallbackImg": "https://images.unsplash.com/photo-1494522855154-9297ac14b55f?auto=format&fit=crop&w=1200&q=80"
    },
    {
      "id": "rss_8",
      "title": "唯一突破鈴木駿輔　陳晨威讚前隊友如山本由伸",
      "description": "（中央社記者蘇志畬桃園21日電）富邦悍將先發投手鈴木駿輔昨天投出9局完封勝，2次被上壘都栽在樂天桃猿隊打者陳晨威手中，過去同隊交情，讓陳晨威對毀了完全比賽感到抱歉，但也盛讚他猶如「山本由伸」。",
      "link": "https://tw.sports.yahoo.com/news/%E5%94%AF-%E7%AA%81%E7%A0%B4%E9%88%B4%E6%9C%A8%E9%A7%BF%E8%BC%94-%E9%99%B3%E6%99%A8%E5%A8%81%E8%AE%9A%E5%89%8D%E9%9A%8A%E5%8F%8B%E5%A6%82%E5%B1%B1%E6%9C%AC%E7%94%B1%E4%BC%B8-095410112.html",
      "pubDate": "6/21 1:54",
      "rawImg": "",
      "fallbackImg": "https://images.unsplash.com/photo-1579952363873-27f3bade9f55?auto=format&fit=crop&w=1200&q=80"
    },
    {
      "id": "rss_9",
      "title": "中職》前兩場完美封鎖兄弟 銳力獅今卻投出本季最短先發",
      "description": "統一獅隊今年聘用曾效力韓職三星獅的洋投銳力獅，截至今天為止，銳力獅面對多年前差點加入的中信兄弟，投得最有心得。但今天雙方再戰，兄弟打者突破他的投球，讓他今僅投4局退場。銳力獅首局連拿兩出局，卻被許基宏擊出二壘打，首局雖度過失分危機，但3局上又遭遇危機，該局他雖連投2次三振，但被張仁瑋、張士綸連續安打",
      "link": "https://tw.sports.yahoo.com/news/%E4%B8%AD%E8%81%B7-%E5%89%8D%E5%85%A9%E5%A0%B4%E5%AE%8C%E7%BE%8E%E5%B0%81%E9%8E%96%E5%85%84%E5%BC%9F-%E9%8A%B3%E5%8A%9B%E7%8D%85%E4%BB%8A%E5%8D%BB%E6%8A%95%E5%87%BA%E6%9C%AC%E5%AD%A3%E6%9C%80%E7%9F%AD%E5%85%88%E7%99%BC-093650744.html",
      "pubDate": "6/21 1:36",
      "rawImg": "https://media.zenfs.com/ko/libertytimes_786/8863fd9ba1f4a94e422759aeb07a55c2",
      "fallbackImg": "https://images.unsplash.com/photo-1508344928928-7137b29de216?auto=format&fit=crop&w=1200&q=80"
    },
    {
      "id": "rss_10",
      "title": "中職》最重用本土先發隊伍 台鋼拚季冠軍必須靠他",
      "description": "台鋼雄鷹今天推派黃子鵬對上味全龍，本季第28場土投扛先發，全聯盟最多，比上半季冠軍味全龍多用21場，戰績仍維持在A段班的第3，放眼下半季要競逐季冠軍，扣除仰賴後勁儘速復活，更寄望第3號先發土投的竄起。台鋼起用洋砲魔鷹，先發輪值比其他球隊少1支洋投，不僅如此，坎南在5月底因肩膀酸痛下二軍，相隔22天才",
      "link": "https://tw.sports.yahoo.com/news/%E4%B8%AD%E8%81%B7-%E6%9C%80%E9%87%8D%E7%94%A8%E6%9C%AC%E5%9C%9F%E5%85%88%E7%99%BC%E9%9A%8A%E4%BC%8D-%E5%8F%B0%E9%8B%BC%E6%8B%9A%E5%AD%A3%E5%86%A0%E8%BB%8D%E5%BF%85%E9%A0%88%E9%9D%A0%E4%BB%96-092506684.html",
      "pubDate": "6/21 1:25",
      "rawImg": "https://media.zenfs.com/ko/libertytimes_786/f09ba38868af77a9ffbf3f94a7f4ae5c",
      "fallbackImg": "https://images.unsplash.com/photo-1544620347-c4fd4a3d5957?auto=format&fit=crop&w=1200&q=80"
    },
    {
      "id": "rss_11",
      "title": "中職》麥斯威尼被降二軍 曾豪駒說的「抹消」變成「註銷」",
      "description": "樂天桃猿昨把洋投麥斯威尼降二軍，對於日前他以中繼登板表現不佳可能是「期末考」，總教練曾豪駒原本的說法是「抹消」，但在賽前聯盟發布正式異動，麥斯威尼卻被「註銷」，新註冊日籍投手榊原元稀。曾豪駒於賽前受訪時指出，目前先把麥斯威尼「抹消」，就是日職的一軍抹消登錄，只是先下二軍。半小時後聯盟收到樂天提交的球",
      "link": "https://tw.sports.yahoo.com/news/%E4%B8%AD%E8%81%B7-%E9%BA%A5%E6%96%AF%E5%A8%81%E5%B0%BC%E8%A2%AB%E9%99%8D%E4%BA%8C%E8%BB%8D-%E6%9B%BE%E8%B1%AA%E9%A7%92%E8%AA%AA%E7%9A%84-%E6%8A%B9%E6%B6%88-%E8%AE%8A%E6%88%90-091917928.html",
      "pubDate": "6/21 1:19",
      "rawImg": "https://media.zenfs.com/ko/libertytimes_786/f24a166362630d0287fe20c0972424ce",
      "fallbackImg": "https://images.unsplash.com/photo-1558000143-a6217b1b3699?auto=format&fit=crop&w=1200&q=80"
    },
    {
      "id": "rss_12",
      "title": "王念好首次守備二壘　後藤光尊先提醒：別太訝異",
      "description": "（中央社記者蘇志畬桃園21日電）中華職棒富邦悍將隊三壘手王念好近日「解鎖」生涯首次鎮守二壘，他笑說是從小到大的第1次，不過總教練後藤光尊早有計畫，也提前提醒「比賽中可能會排，你不要太訝異」。",
      "link": "https://tw.sports.yahoo.com/news/%E7%8E%8B%E5%BF%B5%E5%A5%BD%E9%A6%96%E6%AC%A1%E5%AE%88%E5%82%99%E4%BA%8C%E5%A3%98-%E5%BE%8C%E8%97%A4%E5%85%89%E5%B0%8A%E5%85%88%E6%8F%90%E9%86%92-%E5%88%A5%E5%A4%AA%E8%A8%9D%E7%95%B0-090454073.html",
      "pubDate": "6/21 1:04",
      "rawImg": "",
      "fallbackImg": "https://images.unsplash.com/photo-1494522855154-9297ac14b55f?auto=format&fit=crop&w=1200&q=80"
    },
    {
      "id": "rss_13",
      "title": "中職》曾仁和意外突然退場！ 味全球團回報最新狀況",
      "description": "味全龍先發投手曾仁和今天在2局下被攻下3分大局後，投手教練納瓦洛喊暫停上場關切，未料納瓦洛突然叫防護員上場協助，最終曾仁和因傷退場，改由林鋅杰緊急接替。曾仁和首局無失分，2局下續投被連續敲雙安，雖然抓下2出局，卻被曾子祐和王博玄連續安打失掉3分，納瓦洛喊暫停上丘，最終緊急換投，曾仁和僅投44球1.2",
      "link": "https://tw.sports.yahoo.com/news/%E4%B8%AD%E8%81%B7-%E6%9B%BE%E4%BB%81%E5%92%8C%E6%84%8F%E5%A4%96%E7%AA%81%E7%84%B6%E9%80%80%E5%A0%B4-%E5%91%B3%E5%85%A8%E7%90%83%E5%9C%98%E5%9B%9E%E5%A0%B1%E6%9C%80%E6%96%B0%E7%8B%80%E6%B3%81-090445950.html",
      "pubDate": "6/21 1:04",
      "rawImg": "https://media.zenfs.com/ko/libertytimes_786/a58c52f3c0903d3e7fa2524809df5afc",
      "fallbackImg": "https://images.unsplash.com/photo-1579952363873-27f3bade9f55?auto=format&fit=crop&w=1200&q=80"
    },
    {
      "id": "rss_14",
      "title": "中職》台鋼王牌投手罕見22天沒出賽 原因首度曝光",
      "description": "台鋼雄鷹隊王牌洋投坎南昨相隔22天回一軍，竟然只是在6月的第一場出賽，他透露，其實在5月29日投完樂天桃猿後肩膀酸痛，「所以我才會脫離戰線這麼久。」坎南在5月29日對樂天桃猿飆6局8K無失分好投，連續23局無失分，當時下二軍時，總教練洪一中解釋是因為要讓3洋投輪替，不能讓後勁一直在二軍，不過坎南今天",
      "link": "https://tw.sports.yahoo.com/news/%E4%B8%AD%E8%81%B7-%E5%8F%B0%E9%8B%BC%E7%8E%8B%E7%89%8C%E6%8A%95%E6%89%8B%E7%BD%95%E8%A6%8B22%E5%A4%A9%E6%B2%92%E5%87%BA%E8%B3%BD-%E5%8E%9F%E5%9B%A0%E9%A6%96%E5%BA%A6%E6%9B%9D%E5%85%89-084629155.html",
      "pubDate": "6/21 0:46",
      "rawImg": "https://media.zenfs.com/zh-tw/libertytimes_786/a99fc31f9381a6604f4db192dcb7f337",
      "fallbackImg": "https://images.unsplash.com/photo-1508344928928-7137b29de216?auto=format&fit=crop&w=1200&q=80"
    },
    {
      "id": "rss_15",
      "title": "中職》兄弟「雙張」前兩棒超火燙！兩人週末3戰合計狂敲14安",
      "description": "中信兄弟近期似乎找到前兩棒最佳組合，週末面對統一獅，兄弟連兩場安排張仁瑋、張士綸擔綱前兩棒，兩人火力發揮出色，張仁瑋昨單場4安刷新個人紀錄，今天和張士綸兩人各有雙安演出。...…",
      "link": "https://sports.ltn.com.tw/news/breakingnews/5479341",
      "pubDate": "6/21 11:39",
      "rawImg": "",
      "fallbackImg": "https://images.unsplash.com/photo-1544620347-c4fd4a3d5957?auto=format&fit=crop&w=1200&q=80"
    },
    {
      "id": "rss_16",
      "title": "中職》震撼！台鋼終結者核爆遭KO 龍代打滿貫砲寫聯盟37年首見紀錄",
      "description": "味全龍今天突破台鋼雄鷹隊終結者林詩翔，李凱威在9局上代打夯出追平分滿貫砲，成為中職例行賽史上第一位於9局起夯出代打滿貫砲的客隊選手。\n\n\n味全以1：5落後進入9局上，吉力...…",
      "link": "https://sports.ltn.com.tw/news/breakingnews/5479340",
      "pubDate": "6/21 11:38",
      "rawImg": "",
      "fallbackImg": "https://images.unsplash.com/photo-1558000143-a6217b1b3699?auto=format&fit=crop&w=1200&q=80"
    },
    {
      "id": "rss_17",
      "title": "日職》沒報名中職選秀續留日本！ 台灣鐵捕林家正夯長打+單場雙安",
      "description": "效力日本火腿的台灣鐵捕林家正持續在二軍出賽，今天先發敲出雙安，包含一支二壘安打，近期手感逐漸升溫。\n\n\n林家正面對養樂多二軍先發蹲捕打第8棒，3上首打席逮中小川泰弘的內角高...…",
      "link": "https://sports.ltn.com.tw/news/breakingnews/5479191",
      "pubDate": "6/21 8:59",
      "rawImg": "",
      "fallbackImg": "https://images.unsplash.com/photo-1494522855154-9297ac14b55f?auto=format&fit=crop&w=1200&q=80"
    },
    {
      "id": "rss_18",
      "title": "MLB》只有他辦得到！投手大谷超進化 道奇總監曝改變關鍵",
      "description": "道奇日本二刀流巨星大谷翔平本季繳出7勝、防禦率僅1.47，展現驚人壓制力，表現令人驚艷。道奇投手總監希爾（Rob Hill）近日在播客節目《Pitching Ninja》透...…",
      "link": "https://sports.ltn.com.tw/news/breakingnews/5479162",
      "pubDate": "6/21 8:38",
      "rawImg": "",
      "fallbackImg": "https://images.unsplash.com/photo-1508344928928-7137b29de216?auto=format&fit=crop&w=1200&q=80"
    },
    {
      "id": "rss_19",
      "title": "中職》樂天桃猿註銷麥斯威尼 註冊日籍榊原元稀",
      "description": "樂天桃猿今天做出重大球員異動，昨天降二軍的洋投麥斯威尼被註冊註銷，新註冊日籍投手榊原元稀，預計下週會在補賽週分攤1場先發，麥斯威尼是本季繼中信兄弟黎克後第2位被註銷的外籍...…",
      "link": "https://sports.ltn.com.tw/news/breakingnews/5479198",
      "pubDate": "6/21 8:25",
      "rawImg": "",
      "fallbackImg": "https://images.unsplash.com/photo-1544620347-c4fd4a3d5957?auto=format&fit=crop&w=1200&q=80"
    },
    {
      "id": "rss_20",
      "title": "中職》味全封王微調輪值 最速154公里火球男有望亮相！",
      "description": "味全龍勇奪上半季冠軍，以洋投為主的先發輪值將微調，封王戰MVP鋼龍今天下二軍休養，龍隊在上半季尾聲有意拉上第一指名黃暐傑出賽。\n\n\n龍隊上半季的55場比賽有高達48場使用...…",
      "link": "https://sports.ltn.com.tw/news/breakingnews/5479175",
      "pubDate": "6/21 8:06",
      "rawImg": "",
      "fallbackImg": "https://images.unsplash.com/photo-1558000143-a6217b1b3699?auto=format&fit=crop&w=1200&q=80"
    },
    {
      "id": "rss_21",
      "title": "中職》坎南批抗議手套荒謬 古久保健二回應了！",
      "description": "台鋼雄鷹坎南昨被味全龍抗議手套顏色，罕見在前3局換3咖手套，龍隊總教練葉君璋賽後透露是古久保健二發現異狀。即便坎南說生涯沒遇過這種事，之前用也沒問題，直呼荒謬。對此，古久...…",
      "link": "https://sports.ltn.com.tw/news/breakingnews/5479174",
      "pubDate": "6/21 8:05",
      "rawImg": "",
      "fallbackImg": "https://images.unsplash.com/photo-1494522855154-9297ac14b55f?auto=format&fit=crop&w=1200&q=80"
    },
    {
      "id": "rss_22",
      "title": "中職》投球生涯沒遇過！遭味全抗議手套 坎南：好荒謬",
      "description": "台鋼雄鷹坎南昨被味全龍抗議手套顏色，罕見在前3局換3咖手套，他今天直言投球生涯沒遇過這種事情，「很荒謬，他們不會因為我換手套就得分。」不過他也把握機會為手套廠商「業配」，...…",
      "link": "https://sports.ltn.com.tw/news/breakingnews/5479098",
      "pubDate": "6/21 6:28",
      "rawImg": "",
      "fallbackImg": "https://images.unsplash.com/photo-1579952363873-27f3bade9f55?auto=format&fit=crop&w=1200&q=80"
    },
    {
      "id": "rss_23",
      "title": "MLB》大谷「二寶爸之力」184公里怪力彈！持續推高大聯盟最狂障礙",
      "description": "道奇日本巨星大谷翔平昨天請陪產假缺陣，今天馬上回歸先發打線發揮「二寶爸」之力，敲出本季第16轟，也持續堆高屬於他自己的怪力障礙。\n\n\n大谷昨天與愛妻真美子迎來「二寶」誕生，...…",
      "link": "https://sports.ltn.com.tw/news/breakingnews/5479073",
      "pubDate": "6/21 6:05",
      "rawImg": "",
      "fallbackImg": "https://images.unsplash.com/photo-1508344928928-7137b29de216?auto=format&fit=crop&w=1200&q=80"
    },
    {
      "id": "rss_24",
      "title": "MLB》當二寶爸後首戰開轟！大谷翔平賽後火速返家 道奇主帥說話了",
      "description": "道奇日本巨星大谷翔平昨天喜迎第二胎請陪產假缺陣，今天立刻回到先發打線，並在9局下敲出本季第16轟。賽後大谷並未受訪，並在比賽結束後12分鐘內就閃電返家。\n\n\n大谷昨天與愛妻...…",
      "link": "https://sports.ltn.com.tw/news/breakingnews/5479061",
      "pubDate": "6/21 5:49",
      "rawImg": "",
      "fallbackImg": "https://images.unsplash.com/photo-1544620347-c4fd4a3d5957?auto=format&fit=crop&w=1200&q=80"
    }
  ]
}